Metadata-Version: 2.1
Name: napari-hello
Version: 0.1.0
Summary: My napari plugin
Author: Your Name
Author-email: your.email@example.com
Classifier: Framework :: napari
